pytoolkit/__init__.py
pytoolkit/operation_file/__init__.py
pytoolkit/operation_file/conf_parser.py
pytoolkit/operation_file/csv_utils.py
pytoolkit/operation_file/excel_tools.py
pytoolkit/operation_kafka/__init__.py
pytoolkit/operation_kafka/kafka_utils.py
pytoolkit/operation_mysql/__init__.py
pytoolkit/operation_mysql/mysql_utils.py
pytoolkit/operation_mysql/pyoop.py
pytoolkit/operation_mysql/sqlmy.py
pytoolkit/operation_redis/__init__.py
pytoolkit/operation_redis/redis_utils.py
pytoolkitpro-0.1.1.dist-info/LICENSE
pytoolkitpro-0.1.1.dist-info/METADATA
pytoolkitpro-0.1.1.dist-info/WHEEL
pytoolkitpro-0.1.1.dist-info/top_level.txt
pytoolkitpro-0.1.1.dist-info/RECORD
