Metadata-Version: 2.1
Name: pytoolkitpro
Version: 0.1.1
Summary: pytoolkit
Author: boyi.zhang
Author-email: 15813380401@163.com
License-File: LICENSE
